{
  "id": "ce-mock-11",
  "title": "CE Mock 11 — Full Syllabus (Premium)",
  "tier": "premium",
  "duration": 180,
  "pattern": "GATE 2027 CE (65 Q · 100 marks · 3 hours)",
  "totalMarks": 100,
  "sections": [
    {
      "name": "General Aptitude",
      "count": 10,
      "marks": 15
    },
    {
      "name": "Technical (1-mark)",
      "count": 25,
      "marks": 25
    },
    {
      "name": "Technical (2-mark)",
      "count": 30,
      "marks": 60
    }
  ],
  "negativeMarking": {
    "mcq1": -0.3333333333333333,
    "mcq2": -0.6666666666666666,
    "nat": 0,
    "msq": 0
  },
  "seed": 1485587491,
  "locked": false,
  "questions": [
    {
      "id": 1,
      "subject": "General Aptitude",
      "topic": "Data Interpretation",
      "section": "General Aptitude",
      "type": "NAT",
      "marks": 1,
      "difficulty": "easy",
      "stem": "Compute the average of the four bar values shown: $4, 6, 8, 10$.",
      "answer": 7,
      "tolerance": 0.1,
      "figure": {
        "kind": "svg",
        "caption": "Bar chart of four values",
        "markup": "<svg viewBox='0 0 220 150' xmlns='http://www.w3.org/2000/svg'><line x1='30' y1='120' x2='210' y2='120' stroke='#475569'/><g fill='#bfdbfe' stroke='#475569'><rect x='45' y='90' width='25' height='30'/><rect x='85' y='75' width='25' height='45'/><rect x='125' y='60' width='25' height='60'/><rect x='165' y='45' width='25' height='75'/></g><text x='55' y='138' font-size='8'>4, 6, 8, 10</text></svg>"
      },
      "solution": "**Concept.** Average $=\\dfrac{\\sum x}{n}$.\n\n**Working.**\n$$\\bar{x}=\\frac{4+6+8+10}{4}=\\frac{28}{4}=7$$\n\n**Answer.** $7$."
    },
    {
      "id": 2,
      "subject": "General Aptitude",
      "topic": "Verbal Aptitude — Grammar",
      "section": "General Aptitude",
      "type": "MCQ",
      "marks": 1,
      "difficulty": "easy",
      "stem": "Choose the option that correctly completes the sentence: 'By the time the rescue team arrived, the trapped miners ____ for nearly ten hours.'",
      "options": [
        "had been waiting",
        "have been waiting",
        "are waiting",
        "will wait"
      ],
      "answer": 0,
      "solution": "**Concept.** An action continuing up to a point in the past uses the past perfect continuous tense.\n\n**Working.** The reference point ('the team arrived') is in the past, and the waiting was ongoing before it. This requires 'had been + verb-ing'.\n\n**Answer.** had been waiting."
    },
    {
      "id": 3,
      "subject": "General Aptitude",
      "topic": "Quantitative Aptitude — Number System",
      "section": "General Aptitude",
      "type": "NAT",
      "marks": 1,
      "difficulty": "easy",
      "stem": "The square root of $196$ is _____ .",
      "answer": 14,
      "tolerance": 0.01,
      "solution": "**Concept.** Find the number whose square is $196$.\n\n**Working.** $14^2 = 196$.\n\n**Answer.** $14$."
    },
    {
      "id": 4,
      "subject": "General Aptitude",
      "topic": "Geometry",
      "section": "General Aptitude",
      "type": "NAT",
      "marks": 1,
      "difficulty": "easy",
      "stem": "In the right triangle shown, the legs are $6$ and $8$. Compute the hypotenuse.",
      "answer": 10,
      "tolerance": 0.05,
      "figure": {
        "kind": "svg",
        "caption": "Right triangle",
        "markup": "<svg viewBox='0 0 200 160' xmlns='http://www.w3.org/2000/svg'><polygon points='40,130 160,130 40,50' fill='#bfdbfe' stroke='#475569'/><rect x='40' y='118' width='12' height='12' fill='none' stroke='#475569'/><text x='90' y='145' font-size='8'>8</text><text x='15' y='95' font-size='8'>6</text><text x='105' y='80' font-size='8'>hyp?</text></svg>"
      },
      "solution": "**Concept.** $c=\\sqrt{a^2+b^2}$.\n\n**Working.**\n$$c=\\sqrt{6^2+8^2}=\\sqrt{100}=10$$\n\n**Answer.** $10$."
    },
    {
      "id": 5,
      "subject": "General Aptitude",
      "topic": "Verbal Aptitude — Grammar",
      "section": "General Aptitude",
      "type": "MCQ",
      "marks": 1,
      "difficulty": "easy",
      "stem": "Choose the correct comparative form: 'This seam is ____ than the one we mined last year.'",
      "options": [
        "thicker",
        "more thicker",
        "thickest",
        "most thick"
      ],
      "answer": 0,
      "solution": "**Concept.** One-syllable adjectives form the comparative with '-er', and 'than' signals a comparative (not superlative).\n\n**Working.** 'Thick' becomes 'thicker'; 'more thicker' is a double comparative and 'thickest' is superlative.\n\n**Answer.** thicker."
    },
    {
      "id": 6,
      "subject": "General Aptitude",
      "topic": "Analytical Aptitude — Clocks",
      "section": "General Aptitude",
      "type": "NAT",
      "marks": 2,
      "difficulty": "hard",
      "stem": "The angle between the hour and minute hands of a clock at exactly $4{:}00$ is _____ degrees.",
      "answer": 120,
      "tolerance": 0.01,
      "solution": "**Concept.** Angle $=30^\\circ\\times$ (hours between hands).\n\n**Working.** At $4{:}00$ the hands are $4$ marks apart: $4\\times 30^\\circ = 120^\\circ$.\n\n**Answer.** $120$."
    },
    {
      "id": 7,
      "subject": "General Aptitude",
      "topic": "Analytical Aptitude — Syllogism",
      "section": "General Aptitude",
      "type": "MSQ",
      "marks": 2,
      "difficulty": "hard",
      "stem": "Given 'All P are Q' and 'All Q are R' (with P non-empty), which of the following necessarily follow?",
      "options": [
        "All P are R",
        "Some R are P",
        "All R are P",
        "Some Q are R"
      ],
      "answer": [
        0,
        1,
        3
      ],
      "solution": "**Concept.** Apply transitivity and existential import of a non-empty set.\n\n**Working.** P ⊆ Q ⊆ R gives 'All P are R'; since P is non-empty, 'Some R are P' holds; 'All Q are R' gives 'Some Q are R'. 'All R are P' is not implied (R may be larger).\n\n**Answer.** All P are R; Some R are P; Some Q are R."
    },
    {
      "id": 8,
      "subject": "General Aptitude",
      "topic": "Spatial Aptitude — Counting Figures",
      "section": "General Aptitude",
      "type": "NAT",
      "marks": 2,
      "difficulty": "medium",
      "stem": "A triangle is divided into four smaller triangles by joining the midpoints of its sides (shown). The total number of triangles is _____ .",
      "answer": 5,
      "tolerance": 0.01,
      "figure": {
        "kind": "svg",
        "caption": "A triangle with its three midpoints joined, forming four small triangles.",
        "markup": "<svg viewBox='0 0 160 140' xmlns='http://www.w3.org/2000/svg' role='img'><polygon points='80,15 20,120 140,120' fill='none' stroke='#334155' stroke-width='2'/><line x1='50' y1='67' x2='110' y2='67' stroke='#6366f1' stroke-width='2'/><line x1='50' y1='67' x2='80' y2='120' stroke='#6366f1' stroke-width='2'/><line x1='110' y1='67' x2='80' y2='120' stroke='#6366f1' stroke-width='2'/></svg>"
      },
      "solution": "**Concept.** Count the small triangles and the original.\n\n**Working.** Joining midpoints makes $4$ small triangles; with the original large triangle the total is $4+1=5$.\n\n**Answer.** $5$."
    },
    {
      "id": 9,
      "subject": "General Aptitude",
      "topic": "Mensuration",
      "section": "General Aptitude",
      "type": "NAT",
      "marks": 2,
      "difficulty": "hard",
      "stem": "A circle is inscribed in a square of side $10$ (figure). Compute the shaded area outside the circle but inside the square (use $\\pi=3.1416$, two decimals).",
      "answer": 21.46,
      "tolerance": 0.2,
      "figure": {
        "kind": "svg",
        "caption": "Inscribed circle in a square",
        "markup": "<svg viewBox='0 0 180 180' xmlns='http://www.w3.org/2000/svg'><rect x='25' y='25' width='120' height='120' fill='#2563eb'/><circle cx='85' cy='85' r='60' fill='#e5e7eb'/><text x='30' y='168' font-size='8'>square 10, inscribed circle</text></svg>"
      },
      "solution": "**Concept.** Shaded $=$ square area $-$ circle area, with $r=5$.\n\n**Working.**\n$$A=10^2-3.1416(5)^2=100-78.54=21.46$$\n\n**Answer.** $21.46$."
    },
    {
      "id": 10,
      "subject": "General Aptitude",
      "topic": "Quantitative Aptitude — Average",
      "section": "General Aptitude",
      "type": "MCQ",
      "marks": 2,
      "difficulty": "medium",
      "stem": "The average age of $30$ students is $12$ years. When the teacher's age is included, the average rises to $13$ years. The teacher's age is",
      "options": [
        "43 years",
        "42 years",
        "31 years",
        "13 years"
      ],
      "answer": 0,
      "solution": "**Concept.** Total age = average times number of people.\n\n**Working.** Students' total $=30\\times 12=360$; with teacher $=31\\times 13=403$. Teacher $=403-360=43$.\n\n**Answer.** $43$ years."
    },
    {
      "id": 11,
      "subject": "Hydrology & Irrigation",
      "topic": "Runoff — Rational Method",
      "section": "Technical (1-mark)",
      "type": "NAT",
      "marks": 1,
      "difficulty": "medium",
      "stem": "Catchment $10\\,\\text{ha}$, $C=0.6$, intensity $30\\,\\text{mm/hr}$. Peak runoff ($CIA/360$) is _____ m³/s.",
      "answer": 0.5,
      "tolerance": 0.01,
      "solution": "**Concept.** $Q=CIA/360$.\n\n**Working.**\n$$\\dfrac{0.6\\times30\\times10}{360}=0.5.$$\n\n**Answer.** $0.5$"
    },
    {
      "id": 12,
      "subject": "Engineering Mathematics",
      "topic": "Linear Algebra — Eigenvalues",
      "section": "Technical (1-mark)",
      "type": "NAT",
      "marks": 1,
      "difficulty": "easy",
      "stem": "The sum of eigenvalues of a $2\\times2$ matrix with diagonal $5$ and $9$ is _____.",
      "answer": 14,
      "tolerance": 0.001,
      "solution": "**Concept.** Σλ = trace.\n\n**Working.**\n$$5+9=14.$$\n\n**Answer.** $14$"
    },
    {
      "id": 13,
      "subject": "Environmental Engineering",
      "topic": "Water Demand",
      "section": "Technical (1-mark)",
      "type": "NAT",
      "marks": 1,
      "difficulty": "easy",
      "stem": "Population $1,20,000$, demand $150\\,\\text{lpcd}$. Average daily demand is _____ MLD.",
      "answer": 18,
      "tolerance": 0.02,
      "solution": "**Concept.** demand = pop × lpcd.\n\n**Working.**\n$$\\dfrac{120000\\times150}{10^6}=18.$$\n\n**Answer.** $18\\,\\text{MLD}$"
    },
    {
      "id": 14,
      "subject": "Structural Analysis",
      "topic": "Fixed Beam — UDL",
      "section": "Technical (1-mark)",
      "type": "NAT",
      "marks": 1,
      "difficulty": "medium",
      "stem": "Fixed beam, span $7\\,\\text{m}$, UDL $21\\,\\text{kN/m}$. Support moment is _____ kN·m.",
      "answer": 85.75,
      "tolerance": 0.01,
      "solution": "**Concept.** FEM $=wL^2/12$.\n\n**Working.**\n$$\\dfrac{21\\times7^2}{12}=85.75.$$\n\n**Answer.** $85.75\\,\\text{kN·m}$"
    },
    {
      "id": 15,
      "subject": "Soil Mechanics",
      "topic": "Atterberg Limits",
      "section": "Technical (1-mark)",
      "type": "NAT",
      "marks": 1,
      "difficulty": "easy",
      "stem": "Liquid limit $60\\%$, plastic limit $18\\%$. Plasticity index is _____ %.",
      "answer": 42,
      "tolerance": 0.01,
      "solution": "**Concept.** $PI=LL-PL$.\n\n**Working.**\n$$60-18=42.$$\n\n**Answer.** $42\\%$"
    },
    {
      "id": 16,
      "subject": "Geomatics & Surveying",
      "topic": "Tacheometry",
      "section": "Technical (1-mark)",
      "type": "NAT",
      "marks": 1,
      "difficulty": "medium",
      "stem": "Tacheometer $K=100,C=0$, staff intercept $0.65\\,\\text{m}$ (horizontal sight). Horizontal distance is _____ m.",
      "answer": 65,
      "tolerance": 0.1,
      "solution": "**Concept.** $D=KS+C$.\n\n**Working.**\n$$100\\times0.65=65.$$\n\n**Answer.** $65\\,\\text{m}$"
    },
    {
      "id": 17,
      "subject": "Engineering Mechanics",
      "topic": "Centroid",
      "section": "Technical (1-mark)",
      "type": "NAT",
      "marks": 1,
      "difficulty": "easy",
      "stem": "The centroid of a triangular section of height $450\\,\\text{mm}$ lies at a distance of _____ mm from its base.",
      "answer": 150,
      "tolerance": 0.1,
      "solution": "**Concept.** Centroid of a triangle is at $h/3$ from the base.\n\n**Working.**\n$$\\bar y = \\dfrac{450}{3} = 150.$$\n\n**Answer.** $150\\,\\text{mm}$"
    },
    {
      "id": 18,
      "subject": "Engineering Mechanics",
      "topic": "Resultant of Forces",
      "section": "Technical (1-mark)",
      "type": "NAT",
      "marks": 1,
      "difficulty": "medium",
      "stem": "Two forces of $8\\,\\text{kN}$ and $15\\,\\text{kN}$ act at right angles at a point. The magnitude of their resultant is _____ kN.",
      "answer": 17,
      "tolerance": 0.01,
      "solution": "**Concept.** For perpendicular forces $R=\\sqrt{F_1^2+F_2^2}$.\n\n**Working.**\n$$R=\\sqrt{8^2+15^2}=17.$$\n\n**Answer.** $17\\,\\text{kN}$"
    },
    {
      "id": 19,
      "subject": "Transportation Engineering",
      "topic": "Traffic Flow",
      "section": "Technical (1-mark)",
      "type": "NAT",
      "marks": 1,
      "difficulty": "easy",
      "stem": "Density $30\\,\\text{veh/km}$, speed $40\\,\\text{km/h}$. Flow is _____ veh/h.",
      "answer": 1200,
      "tolerance": 1,
      "solution": "**Concept.** $q=kv$.\n\n**Working.**\n$$30\\times40=1200.$$\n\n**Answer.** $1200\\,\\text{veh/h}$"
    },
    {
      "id": 20,
      "subject": "Geomatics & Surveying",
      "topic": "Tacheometry",
      "section": "Technical (1-mark)",
      "type": "NAT",
      "marks": 1,
      "difficulty": "medium",
      "stem": "Tacheometer $K=100,C=0$, staff intercept $1.29\\,\\text{m}$ (horizontal sight). Horizontal distance is _____ m.",
      "answer": 129,
      "tolerance": 0.1,
      "solution": "**Concept.** $D=KS+C$.\n\n**Working.**\n$$100\\times1.29=129.$$\n\n**Answer.** $129\\,\\text{m}$"
    },
    {
      "id": 21,
      "subject": "Engineering Mathematics",
      "topic": "Calculus — Differentiation",
      "section": "Technical (1-mark)",
      "type": "NAT",
      "marks": 1,
      "difficulty": "easy",
      "stem": "The slope of $y=4x^2$ at $x=1$ is _____.",
      "answer": 8,
      "tolerance": 0.001,
      "solution": "**Concept.** $dy/dx=2ax$.\n\n**Working.**\n$$2(4)(1)=8.$$\n\n**Answer.** $8$"
    },
    {
      "id": 22,
      "subject": "Construction Materials & Management",
      "topic": "PERT — Variance",
      "section": "Technical (1-mark)",
      "type": "NAT",
      "marks": 1,
      "difficulty": "medium",
      "stem": "Activity: optimistic $5$, pessimistic $15$ days. Variance is _____ days².",
      "answer": 2.777777777777778,
      "tolerance": 0.05,
      "solution": "**Concept.** $\\sigma^2=((t_p-t_o)/6)^2$.\n\n**Working.**\n$$((15-5)/6)^2=2.78.$$\n\n**Answer.** $2.78$"
    },
    {
      "id": 23,
      "subject": "Steel Structures",
      "topic": "Compression Member",
      "section": "Technical (1-mark)",
      "type": "NAT",
      "marks": 1,
      "difficulty": "easy",
      "stem": "Effective length $4500\\,\\text{mm}$, $r_{min}=30\\,\\text{mm}$. Slenderness ratio is _____.",
      "answer": 150,
      "tolerance": 0.1,
      "solution": "**Concept.** $\\lambda=L_e/r_{min}$.\n\n**Working.**\n$$\\dfrac{4500}{30}=150.$$\n\n**Answer.** $150$"
    },
    {
      "id": 24,
      "subject": "Engineering Mathematics",
      "topic": "Vector Calculus — Dot Product",
      "section": "Technical (1-mark)",
      "type": "NAT",
      "marks": 1,
      "difficulty": "easy",
      "stem": "The dot product $(1\\hat i + 2\\hat j + 2\\hat k)\\cdot(2\\hat i + 0\\hat j + 1\\hat k)$ is _____.",
      "answer": 4,
      "tolerance": 0.001,
      "solution": "**Concept.** $\\vec a\\cdot\\vec b = a_xb_x + a_yb_y + a_zb_z$.\n\n**Working.**\n$$= 1\\cdot2 + 2\\cdot0 + 2\\cdot1 = 4.$$\n\n**Answer.** $4$"
    },
    {
      "id": 25,
      "subject": "Geomatics & Surveying",
      "topic": "Tacheometry",
      "section": "Technical (1-mark)",
      "type": "NAT",
      "marks": 1,
      "difficulty": "medium",
      "stem": "Tacheometer $K=100,C=0$, staff intercept $1.48\\,\\text{m}$ (horizontal sight). Horizontal distance is _____ m.",
      "answer": 148,
      "tolerance": 0.1,
      "solution": "**Concept.** $D=KS+C$.\n\n**Working.**\n$$100\\times1.48=148.$$\n\n**Answer.** $148\\,\\text{m}$"
    },
    {
      "id": 26,
      "subject": "Structural Analysis",
      "topic": "Fixed Beam",
      "section": "Technical (1-mark)",
      "type": "NAT",
      "marks": 1,
      "difficulty": "medium",
      "stem": "A fixed beam of span $6\\,\\text{m}$ carries a central point load $40\\,\\text{kN}$. The magnitude of the fixed-end moment is _____ kN·m.",
      "answer": 30,
      "tolerance": 0.01,
      "solution": "**Concept.** Fixed-end moment for a central point load $=\\dfrac{WL}{8}$.\n\n**Working.**\n$$M=\\dfrac{40\\times 6}{8}=30.$$\n\n**Answer.** $30\\,\\text{kN·m}$"
    },
    {
      "id": 27,
      "subject": "Foundation Engineering",
      "topic": "Pile Foundations",
      "section": "Technical (1-mark)",
      "type": "MCQ",
      "marks": 1,
      "difficulty": "medium",
      "stem": "The group efficiency of a pile group is generally defined as",
      "options": [
        "group capacity ÷ sum of individual pile capacities",
        "sum of pile capacities ÷ group capacity",
        "number of piles × single capacity",
        "settlement ratio"
      ],
      "answer": 0,
      "solution": "**Concept.** $\\eta_g=\\dfrac{Q_{group}}{n Q_{single}}$.\n\n**Working.**\nGroup/Σ individual.\n\n**Answer.** Group ÷ Σ individual"
    },
    {
      "id": 28,
      "subject": "Construction Materials & Management",
      "topic": "PERT — Variance",
      "section": "Technical (1-mark)",
      "type": "NAT",
      "marks": 1,
      "difficulty": "medium",
      "stem": "Activity: optimistic $4$, pessimistic $12$ days. Variance is _____ days².",
      "answer": 1.7777777777777777,
      "tolerance": 0.05,
      "solution": "**Concept.** $\\sigma^2=((t_p-t_o)/6)^2$.\n\n**Working.**\n$$((12-4)/6)^2=1.78.$$\n\n**Answer.** $1.78$"
    },
    {
      "id": 29,
      "subject": "Foundation Engineering",
      "topic": "Safe Bearing Capacity",
      "section": "Technical (1-mark)",
      "type": "NAT",
      "marks": 1,
      "difficulty": "easy",
      "stem": "The ultimate bearing capacity is $300\\,\\text{kPa}$. With a factor of safety of $3$, the net safe bearing capacity (gross basis) is _____ kPa.",
      "answer": 100,
      "tolerance": 0.1,
      "solution": "**Concept.** $q_{safe}=\\dfrac{q_u}{\\text{FoS}}$.\n\n**Working.**\n$$q_{safe}=\\dfrac{300}{3}=100.$$\n\n**Answer.** $100\\,\\text{kPa}$"
    },
    {
      "id": 30,
      "subject": "Hydrology & Irrigation",
      "topic": "Runoff — Rational Method",
      "section": "Technical (1-mark)",
      "type": "NAT",
      "marks": 1,
      "difficulty": "medium",
      "stem": "Catchment $50\\,\\text{ha}$, $C=0.4$, intensity $40\\,\\text{mm/hr}$. Peak runoff ($CIA/360$) is _____ m³/s.",
      "answer": 2.2222222222222223,
      "tolerance": 0.01,
      "solution": "**Concept.** $Q=CIA/360$.\n\n**Working.**\n$$\\dfrac{0.4\\times40\\times50}{360}=2.222.$$\n\n**Answer.** $2.222$"
    },
    {
      "id": 31,
      "subject": "Engineering Mathematics",
      "topic": "Calculus — Integration",
      "section": "Technical (1-mark)",
      "type": "NAT",
      "marks": 1,
      "difficulty": "medium",
      "stem": "Evaluate $\\displaystyle\\int_0^{5} x^{3}\\,dx$.",
      "answer": 156.25,
      "tolerance": 0.01,
      "solution": "**Concept.** $\\int_0^a x^n dx=\\dfrac{a^{n+1}}{n+1}$.\n\n**Working.**\n$$\\dfrac{5^{4}}{4}=156.25.$$\n\n**Answer.** $156.25$"
    },
    {
      "id": 32,
      "subject": "Transportation Engineering",
      "topic": "Traffic Flow",
      "section": "Technical (1-mark)",
      "type": "NAT",
      "marks": 1,
      "difficulty": "easy",
      "stem": "Density $30\\,\\text{veh/km}$, speed $50\\,\\text{km/h}$. Flow is _____ veh/h.",
      "answer": 1500,
      "tolerance": 1,
      "solution": "**Concept.** $q=kv$.\n\n**Working.**\n$$30\\times50=1500.$$\n\n**Answer.** $1500\\,\\text{veh/h}$"
    },
    {
      "id": 33,
      "subject": "Engineering Mechanics",
      "topic": "Bending Moment — UDL",
      "section": "Technical (1-mark)",
      "type": "NAT",
      "marks": 1,
      "difficulty": "medium",
      "stem": "A simply supported beam, span $5\\,\\text{m}$, UDL $20\\,\\text{kN/m}$. Max BM is _____ kN·m.",
      "answer": 62.5,
      "tolerance": 0.01,
      "solution": "**Concept.** $M_{max}=wL^2/8$.\n\n**Working.**\n$$\\dfrac{20\\times5^2}{8}=62.5.$$\n\n**Answer.** $62.5\\,\\text{kN·m}$"
    },
    {
      "id": 34,
      "subject": "Construction Materials & Management",
      "topic": "Cement",
      "section": "Technical (1-mark)",
      "type": "MCQ",
      "marks": 1,
      "difficulty": "easy",
      "stem": "The initial setting time of ordinary Portland cement (as per IS) should not be less than",
      "options": [
        "$30$ minutes",
        "$10$ minutes",
        "$60$ minutes",
        "$600$ minutes"
      ],
      "answer": 0,
      "solution": "**Concept.** IS limit: initial set ≥ 30 min; final set ≤ 600 min.\n\n**Working.**\n$30$ min.\n\n**Answer.** $30$ minutes"
    },
    {
      "id": 35,
      "subject": "Environmental Engineering",
      "topic": "Water Demand",
      "section": "Technical (1-mark)",
      "type": "NAT",
      "marks": 1,
      "difficulty": "easy",
      "stem": "A town of population $50,000$ has a per-capita demand of $150\\,\\text{lpcd}$. The average daily demand is _____ MLD.",
      "answer": 7.5,
      "tolerance": 0.01,
      "solution": "**Concept.** Demand $=$ population × lpcd.\n\n**Working.**\n$$=\\dfrac{50000\\times 150}{10^6}=7.5\\,\\text{MLD}.$$\n\n**Answer.** $7.5\\,\\text{MLD}$"
    },
    {
      "id": 36,
      "subject": "Foundation Engineering",
      "topic": "Bearing Pressure",
      "section": "Technical (2-mark)",
      "type": "NAT",
      "marks": 2,
      "difficulty": "medium",
      "stem": "A footing applies a gross pressure of $200\\,\\text{kPa}$ at depth $1.5\\,\\text{m}$ ($\\gamma=18\\,\\text{kN/m}^3$). The net pressure is _____ kPa.",
      "answer": 173,
      "tolerance": 0.1,
      "solution": "**Concept.** $q_{net}=q_{gross}-\\gamma D_f$.\n\n**Working.**\n$$q_{net}=200-18\\times 1.5=173.$$\n\n**Answer.** $173\\,\\text{kPa}$"
    },
    {
      "id": 37,
      "subject": "Structural Analysis",
      "topic": "Fixed Beam — UDL",
      "section": "Technical (2-mark)",
      "type": "NAT",
      "marks": 2,
      "difficulty": "medium",
      "stem": "Fixed beam, span $7\\,\\text{m}$, UDL $11\\,\\text{kN/m}$. Support moment is _____ kN·m.",
      "answer": 44.916666666666664,
      "tolerance": 0.01,
      "solution": "**Concept.** FEM $=wL^2/12$.\n\n**Working.**\n$$\\dfrac{11\\times7^2}{12}=44.92.$$\n\n**Answer.** $44.92\\,\\text{kN·m}$"
    },
    {
      "id": 38,
      "subject": "RCC & Prestressed Concrete",
      "topic": "Development Length",
      "section": "Technical (2-mark)",
      "type": "NAT",
      "marks": 2,
      "difficulty": "hard",
      "stem": "For a bar of diameter $\\phi = 16\\,\\text{mm}$ with design bond stress giving $L_d = 47\\phi$, the development length is _____ mm.",
      "answer": 752,
      "tolerance": 1,
      "solution": "**Concept.** $L_d = 47\\phi$ (given).\n\n**Working.**\n$$L_d = 47\\times 16 = 752.$$\n\n**Answer.** $752\\,\\text{mm}$"
    },
    {
      "id": 39,
      "subject": "Engineering Mechanics",
      "topic": "Bending Moment",
      "section": "Technical (2-mark)",
      "type": "NAT",
      "marks": 2,
      "difficulty": "medium",
      "stem": "A simply supported beam, span $8\\,\\text{m}$, central point load $34\\,\\text{kN}$. Max BM is _____ kN·m.",
      "answer": 68,
      "tolerance": 0.01,
      "solution": "**Concept.** $M_{max}=WL/4$.\n\n**Working.**\n$$\\dfrac{34\\times8}{4}=68.$$\n\n**Answer.** $68\\,\\text{kN·m}$"
    },
    {
      "id": 40,
      "subject": "Environmental Engineering",
      "topic": "BOD",
      "section": "Technical (2-mark)",
      "type": "NAT",
      "marks": 2,
      "difficulty": "hard",
      "stem": "Ultimate BOD $200\\,\\text{mg/L}$, $k=0.12\\,\\text{d}^{-1}$ (base 10). BOD exerted in $5$ days is _____ mg/L.",
      "answer": 149.7622713698084,
      "tolerance": 0.5,
      "solution": "**Concept.** $y_t=L_0(1-10^{-kt})$.\n\n**Working.**\n$$200(1-10^{-0.12\\times5})=149.8.$$\n\n**Answer.** $149.8$"
    },
    {
      "id": 41,
      "subject": "Engineering Mechanics",
      "topic": "Beam Reactions — UDL",
      "section": "Technical (2-mark)",
      "type": "NAT",
      "marks": 2,
      "difficulty": "medium",
      "stem": "A simply supported beam of span $6\\,\\text{m}$ carries a UDL of $20\\,\\text{kN/m}$ over its full length. Each support reaction is _____ kN.",
      "answer": 60,
      "tolerance": 0.01,
      "solution": "**Concept.** Total load $=wL$; each reaction $=wL/2$.\n\n**Working.**\n$$R = \\dfrac{20\\times 6}{2} = 60.$$\n\n**Answer.** $60\\,\\text{kN}$"
    },
    {
      "id": 42,
      "subject": "Foundation Engineering",
      "topic": "Bearing Pressure",
      "section": "Technical (2-mark)",
      "type": "NAT",
      "marks": 2,
      "difficulty": "medium",
      "stem": "Gross pressure $180\\,\\text{kPa}$ at depth $1\\,\\text{m}$, $\\gamma=20\\,\\text{kN/m}^3$. Net pressure is _____ kPa.",
      "answer": 160,
      "tolerance": 0.1,
      "solution": "**Concept.** $q_{net}=q-\\gamma D_f$.\n\n**Working.**\n$$180-20\\times1=160.$$\n\n**Answer.** $160\\,\\text{kPa}$"
    },
    {
      "id": 43,
      "subject": "Foundation Engineering",
      "topic": "Earth Pressure",
      "section": "Technical (2-mark)",
      "type": "NAT",
      "marks": 2,
      "difficulty": "medium",
      "stem": "For a cohesionless backfill with $\\phi=30^\\circ$, the Rankine active earth pressure coefficient $K_a$ is _____.",
      "answer": 0.3333,
      "tolerance": 0.01,
      "solution": "**Concept.** $K_a=\\dfrac{1-\\sin\\phi}{1+\\sin\\phi}$.\n\n**Working.**\n$$K_a=\\dfrac{1-\\sin 30^\\circ}{1+\\sin 30^\\circ}=0.333.$$\n\n**Answer.** $0.333$"
    },
    {
      "id": 44,
      "subject": "Soil Mechanics",
      "topic": "Unit Weight",
      "section": "Technical (2-mark)",
      "type": "NAT",
      "marks": 2,
      "difficulty": "medium",
      "stem": "Bulk unit weight $18\\,\\text{kN/m}^3$, water content $25\\%$. Dry unit weight is _____ kN/m³.",
      "answer": 14.4,
      "tolerance": 0.02,
      "solution": "**Concept.** $\\gamma_d=\\gamma/(1+w)$.\n\n**Working.**\n$$\\dfrac{18}{1+0.25}=14.4.$$\n\n**Answer.** $14.4$"
    },
    {
      "id": 45,
      "subject": "Construction Materials & Management",
      "topic": "PERT — Variance",
      "section": "Technical (2-mark)",
      "type": "NAT",
      "marks": 2,
      "difficulty": "medium",
      "stem": "Activity: optimistic $4$, pessimistic $16$ days. Variance is _____ days².",
      "answer": 4,
      "tolerance": 0.05,
      "solution": "**Concept.** $\\sigma^2=((t_p-t_o)/6)^2$.\n\n**Working.**\n$$((16-4)/6)^2=4.$$\n\n**Answer.** $4$"
    },
    {
      "id": 46,
      "subject": "Hydrology & Irrigation",
      "topic": "Irrigation — Delta",
      "section": "Technical (2-mark)",
      "type": "NAT",
      "marks": 2,
      "difficulty": "medium",
      "stem": "Base period $90\\,\\text{days}$, duty $700\\,\\text{ha/cumec}$. Delta is _____ m.",
      "answer": 1.110857142857143,
      "tolerance": 0.005,
      "solution": "**Concept.** $\\Delta=8.64B/D$.\n\n**Working.**\n$$\\dfrac{8.64\\times90}{700}=1.111.$$\n\n**Answer.** $1.111\\,\\text{m}$"
    },
    {
      "id": 47,
      "subject": "Fluid Mechanics & Hydraulics",
      "topic": "Open Channel — Manning",
      "section": "Technical (2-mark)",
      "type": "NAT",
      "marks": 2,
      "difficulty": "hard",
      "stem": "Manning $n=0.012$, $R=0.8\\,\\text{m}$, $S=0.0008$. Mean velocity is _____ m/s.",
      "answer": 2.03122050526011,
      "tolerance": 0.02,
      "solution": "**Concept.** $v=\\dfrac1n R^{2/3}S^{1/2}$.\n\n**Working.**\n$$\\dfrac{1}{0.012}(0.8)^{2/3}(0.0008)^{1/2}=2.031.$$\n\n**Answer.** $2.031$"
    },
    {
      "id": 48,
      "subject": "RCC & Prestressed Concrete",
      "topic": "Limit State — Stress Block",
      "section": "Technical (2-mark)",
      "type": "NAT",
      "marks": 2,
      "difficulty": "hard",
      "stem": "Singly-reinforced beam: $b=300$, $A_{st}=1200\\,\\text{mm}^2$, Fe415, M20. Stress-block depth $x_u$ is _____ mm.",
      "answer": 200.58333333333334,
      "tolerance": 1,
      "solution": "**Concept.** $0.36f_{ck}bx_u=0.87f_yA_{st}$.\n\n**Working.**\n$$\\dfrac{0.87\\times415\\times1200}{0.36\\times20\\times300}=200.6.$$\n\n**Answer.** $200.6\\,\\text{mm}$"
    },
    {
      "id": 49,
      "subject": "RCC & Prestressed Concrete",
      "topic": "Limit State — Stress Block",
      "section": "Technical (2-mark)",
      "type": "NAT",
      "marks": 2,
      "difficulty": "hard",
      "stem": "Singly-reinforced beam: $b=300$, $A_{st}=900\\,\\text{mm}^2$, Fe415, M30. Stress-block depth $x_u$ is _____ mm.",
      "answer": 100.29166666666669,
      "tolerance": 1,
      "solution": "**Concept.** $0.36f_{ck}bx_u=0.87f_yA_{st}$.\n\n**Working.**\n$$\\dfrac{0.87\\times415\\times900}{0.36\\times30\\times300}=100.3.$$\n\n**Answer.** $100.3\\,\\text{mm}$"
    },
    {
      "id": 50,
      "subject": "Structural Analysis",
      "topic": "Fixed Beam",
      "section": "Technical (2-mark)",
      "type": "NAT",
      "marks": 2,
      "difficulty": "medium",
      "stem": "A fixed beam of span $4\\,\\text{m}$ carries a central point load $60\\,\\text{kN}$. The magnitude of the fixed-end moment is _____ kN·m.",
      "answer": 30,
      "tolerance": 0.01,
      "solution": "**Concept.** Fixed-end moment for a central point load $=\\dfrac{WL}{8}$.\n\n**Working.**\n$$M=\\dfrac{60\\times 4}{8}=30.$$\n\n**Answer.** $30\\,\\text{kN·m}$"
    },
    {
      "id": 51,
      "subject": "Construction Materials & Management",
      "topic": "PERT",
      "section": "Technical (2-mark)",
      "type": "NAT",
      "marks": 2,
      "difficulty": "medium",
      "stem": "Activity: optimistic $2$, most-likely $9$, pessimistic $16$ days. PERT expected time is _____ days.",
      "answer": 9,
      "tolerance": 0.05,
      "solution": "**Concept.** $t_e=(t_o+4t_m+t_p)/6$.\n\n**Working.**\n$$\\dfrac{2+4(9)+16}{6}=9.$$\n\n**Answer.** $9$"
    },
    {
      "id": 52,
      "subject": "Construction Materials & Management",
      "topic": "PERT — Variance",
      "section": "Technical (2-mark)",
      "type": "NAT",
      "marks": 2,
      "difficulty": "medium",
      "stem": "Activity: optimistic $4$, pessimistic $15$ days. Variance is _____ days².",
      "answer": 3.3611111111111107,
      "tolerance": 0.05,
      "solution": "**Concept.** $\\sigma^2=((t_p-t_o)/6)^2$.\n\n**Working.**\n$$((15-4)/6)^2=3.36.$$\n\n**Answer.** $3.36$"
    },
    {
      "id": 53,
      "subject": "Soil Mechanics",
      "topic": "Earth Pressure",
      "section": "Technical (2-mark)",
      "type": "NAT",
      "marks": 2,
      "difficulty": "medium",
      "stem": "Cohesionless backfill $\\phi=34^\\circ$. Rankine active coefficient $K_a$ is _____.",
      "answer": 0.2827149197177727,
      "tolerance": 0.005,
      "solution": "**Concept.** $K_a=(1-\\sin\\phi)/(1+\\sin\\phi)$.\n\n**Working.**\n$$\\dfrac{1-\\sin34}{1+\\sin34}=0.283.$$\n\n**Answer.** $0.283$"
    },
    {
      "id": 54,
      "subject": "Transportation Engineering",
      "topic": "Geometric Design",
      "section": "Technical (2-mark)",
      "type": "MSQ",
      "marks": 2,
      "difficulty": "hard",
      "stem": "Which factors are considered while fixing the ruling gradient of a highway?",
      "options": [
        "Power of the design vehicle",
        "Length of the gradient",
        "Pavement colour",
        "Speed to be maintained"
      ],
      "answer": [
        0,
        1,
        3
      ],
      "solution": "**Concept.** Ruling gradient depends on vehicle power, gradient length and speed; pavement colour is irrelevant.\n\n**Working.**\nOptions 1, 2, 4.\n\n**Answer.** Vehicle power, length, speed"
    },
    {
      "id": 55,
      "subject": "Solid Mechanics",
      "topic": "Axial Deformation",
      "section": "Technical (2-mark)",
      "type": "NAT",
      "marks": 2,
      "difficulty": "medium",
      "stem": "Steel bar ($E=200\\,\\text{GPa}$), area $500\\,\\text{mm}^2$, length $1000\\,\\text{mm}$, load $54\\,\\text{kN}$. Elongation is _____ mm.",
      "answer": 0.54,
      "tolerance": 0.005,
      "solution": "**Concept.** $\\delta=PL/AE$.\n\n**Working.**\n$$\\dfrac{54\\times10^3\\times1000}{500\\times200000}=0.54.$$\n\n**Answer.** $0.54\\,\\text{mm}$"
    },
    {
      "id": 56,
      "subject": "Steel Structures",
      "topic": "Tension Member",
      "section": "Technical (2-mark)",
      "type": "NAT",
      "marks": 2,
      "difficulty": "medium",
      "stem": "A tension member of gross area $2000\\,\\text{mm}^2$ (Fe$250$, $\\gamma_{m0}=1.1$) has design strength governed by gross yielding $=\\dfrac{A_g f_y}{\\gamma_{m0}}$ = _____ kN.",
      "answer": 454.5455,
      "tolerance": 0.1,
      "solution": "**Concept.** Gross-section yielding: $T_{dg}=\\dfrac{A_g f_y}{\\gamma_{m0}}$.\n\n**Working.**\n$$T_{dg}=\\dfrac{2000\\times 250}{1.1\\times 1000}=454.55.$$\n\n**Answer.** $454.55\\,\\text{kN}$"
    },
    {
      "id": 57,
      "subject": "Soil Mechanics",
      "topic": "Unit Weight",
      "section": "Technical (2-mark)",
      "type": "NAT",
      "marks": 2,
      "difficulty": "medium",
      "stem": "A soil has bulk unit weight $19\\,\\text{kN/m}^3$ and water content $20\\%$. Its dry unit weight is _____ kN/m³.",
      "answer": 15.8333,
      "tolerance": 0.01,
      "solution": "**Concept.** $\\gamma_d=\\dfrac{\\gamma}{1+w}$.\n\n**Working.**\n$$\\gamma_d=\\dfrac{19}{1+0.2}=15.83.$$\n\n**Answer.** $15.83\\,\\text{kN/m}^3$"
    },
    {
      "id": 58,
      "subject": "Environmental Engineering",
      "topic": "BOD",
      "section": "Technical (2-mark)",
      "type": "NAT",
      "marks": 2,
      "difficulty": "hard",
      "stem": "Ultimate BOD $200\\,\\text{mg/L}$, $k=0.12\\,\\text{d}^{-1}$ (base 10). BOD exerted in $7$ days is _____ mg/L.",
      "answer": 171.09120458508144,
      "tolerance": 0.5,
      "solution": "**Concept.** $y_t=L_0(1-10^{-kt})$.\n\n**Working.**\n$$200(1-10^{-0.12\\times7})=171.1.$$\n\n**Answer.** $171.1$"
    },
    {
      "id": 59,
      "subject": "Fluid Mechanics & Hydraulics",
      "topic": "Open Channel — Manning",
      "section": "Technical (2-mark)",
      "type": "NAT",
      "marks": 2,
      "difficulty": "hard",
      "stem": "Manning $n=0.013$, $R=0.8\\,\\text{m}$, $S=0.001$. Mean velocity is _____ m/s.",
      "answer": 2.096283289409112,
      "tolerance": 0.02,
      "solution": "**Concept.** $v=\\dfrac1n R^{2/3}S^{1/2}$.\n\n**Working.**\n$$\\dfrac{1}{0.013}(0.8)^{2/3}(0.001)^{1/2}=2.096.$$\n\n**Answer.** $2.096$"
    },
    {
      "id": 60,
      "subject": "Geomatics & Surveying",
      "topic": "Modern Surveying",
      "section": "Technical (2-mark)",
      "type": "MSQ",
      "marks": 2,
      "difficulty": "medium",
      "stem": "Which statements about contour lines are correct?",
      "options": [
        "Contours of different elevations never cross (except at a cliff/overhang)",
        "Closely spaced contours indicate steep ground",
        "Contours always form straight lines",
        "A contour line joins points of equal elevation"
      ],
      "answer": [
        0,
        1,
        3
      ],
      "solution": "**Concept.** Contours join equal elevations, crowd on steep ground and don't cross except at overhangs; they are not straight in general.\n\n**Working.**\nOptions 1, 2, 4.\n\n**Answer.** Equal elevation, steep crowding, no crossing"
    },
    {
      "id": 61,
      "subject": "Engineering Mechanics",
      "topic": "Bending Moment — UDL",
      "section": "Technical (2-mark)",
      "type": "NAT",
      "marks": 2,
      "difficulty": "medium",
      "stem": "A simply supported beam of span $6\\,\\text{m}$ carries a UDL of $20\\,\\text{kN/m}$. The maximum bending moment is _____ kN·m.",
      "answer": 90,
      "tolerance": 0.01,
      "solution": "**Concept.** For a full UDL $M_{max}=\\dfrac{wL^2}{8}$.\n\n**Working.**\n$$M_{max}=\\dfrac{20\\times 6^2}{8}=90.$$\n\n**Answer.** $90\\,\\text{kN·m}$"
    },
    {
      "id": 62,
      "subject": "Soil Mechanics",
      "topic": "Unit Weight",
      "section": "Technical (2-mark)",
      "type": "NAT",
      "marks": 2,
      "difficulty": "medium",
      "stem": "A soil has bulk unit weight $20\\,\\text{kN/m}^3$ and water content $25\\%$. Its dry unit weight is _____ kN/m³.",
      "answer": 16,
      "tolerance": 0.01,
      "solution": "**Concept.** $\\gamma_d=\\dfrac{\\gamma}{1+w}$.\n\n**Working.**\n$$\\gamma_d=\\dfrac{20}{1+0.25}=16.$$\n\n**Answer.** $16\\,\\text{kN/m}^3$"
    },
    {
      "id": 63,
      "subject": "Fluid Mechanics & Hydraulics",
      "topic": "Reynolds Number",
      "section": "Technical (2-mark)",
      "type": "NAT",
      "marks": 2,
      "difficulty": "medium",
      "stem": "Water ($\\nu=10^{-6}\\,\\text{m}^2/\\text{s}$) flows at $2\\,\\text{m/s}$ in a $100\\,\\text{mm}$ diameter pipe. The Reynolds number is _____.",
      "answer": 200000,
      "tolerance": 1,
      "solution": "**Concept.** $Re=\\dfrac{vD}{\\nu}$.\n\n**Working.**\n$$Re=\\dfrac{2\\times 0.1}{0.000001}=200000.$$\n\n**Answer.** $200000$"
    },
    {
      "id": 64,
      "subject": "Construction Materials & Management",
      "topic": "CPM — Float",
      "section": "Technical (2-mark)",
      "type": "NAT",
      "marks": 2,
      "difficulty": "medium",
      "stem": "An activity has EST $=5$, LST $=8$ days. Its total float is _____ days.",
      "answer": 3,
      "tolerance": 0.01,
      "solution": "**Concept.** Total float $=\\text{LST}-\\text{EST}$.\n\n**Working.**\n$$TF=8-5=3.$$\n\n**Answer.** $3\\,\\text{days}$"
    },
    {
      "id": 65,
      "subject": "Soil Mechanics",
      "topic": "Permeability — Darcy",
      "section": "Technical (2-mark)",
      "type": "NAT",
      "marks": 2,
      "difficulty": "medium",
      "stem": "A soil has coefficient of permeability $k = 0.0002\\,\\text{m/s}$ and is subjected to a hydraulic gradient $i = 0.8$. The Darcy (discharge) velocity is _____ m/s.",
      "answer": 0.0002,
      "tolerance": 1.6e-7,
      "solution": "**Concept.** $v=ki$ (Darcy's law).\n\n**Working.**\n$$v=0.0002\\times 0.8=1.60e-4.$$\n\n**Answer.** $1.60e-4\\,\\text{m/s}$"
    }
  ]
}
